{
  "toDos": [
    {
      "title": "asdf",
      "todo": "asdf",
      "isDone": 1,
      "createdAt": "2023.12.13 23:35:20",
      "id": 3
    },
    {
      "title": "dfasdfasd",
      "todo": "fasdfawefawef",
      "isDone": 1,
      "createdAt": "2023.12.13 23:35:26",
      "id": 4
    },
    {
      "title": "ㅁㄴㅇㄹㅁㅈ",
      "todo": "ㅁㅈㄹㅊㅍㅁㅇㄹㅁㅈㄷㄹ",
      "isDone": 0,
      "createdAt": "2023.12.13 23:40:15",
      "id": 9
    },
    {
      "title": "test",
      "todo": "1234",
      "isDone": 0,
      "createdAt": "2023.12.14 11:52:20",
      "id": 10
    },
    {
      "title": "vcvasdf",
      "todo": "aefawef",
      "isDone": 0,
      "createdAt": "2023.12.14 11:56:11",
      "id": 14
    },
    {
      "title": "어머어머.. 포크.. 떠가셈..?",
      "todo": "포크",
      "isDone": 0,
      "createdAt": "2023.12.14 14:31:16",
      "id": 15
    },
    {
      "title": "loading test",
      "todo": "loadingtest",
      "isDone": 0,
      "createdAt": "2023.12.14 16:00:25",
      "id": 16
    }
  ]
}